Metadata-Version: 2.1
Name: python-mysql2postgresql
Version: 0.1.1
Summary: python-mysql2postgresql
Author: DewBloodmetal
Author-email: dewscan001@gmail.com
Keywords: python mysql2postgresql python-mysql2postgresql
Classifier: Development Status :: 3 - Alpha
Classifier: Programming Language :: Python
Classifier: Programming Language :: Python :: 3
Classifier: Topic :: Database
